emmi/__init__.py
emmi/_version.py
emmi/app.py
emmi/scpi.py
emmi/api/__init__.py
emmi/api/exports.py
emmi/api/motor.py
emmi/api/caproto/__init__.py
emmi/api/caproto/motor.py
emmi/ca/format.py
emmi/ca/histo.py
emmi/ca/reader.py
emmi/eda/__init__.py
emmi/eda/motor.py
emmi/eda/worker.py
emmi-0.10.3.dist-info/LICENSE
emmi-0.10.3.dist-info/METADATA
emmi-0.10.3.dist-info/WHEEL
emmi-0.10.3.dist-info/top_level.txt
emmi-0.10.3.dist-info/RECORD
