Metadata-Version: 2.2
Name: emmi
Version: 0.10.3
Summary: A Selection of Tools for EPICS Monday-Morning Integrations
Author-email: Matthias Rössle <matthias.roessle@helmholtz-berlin.de>, Florin Boariu <florin.pt@rootshell.ro>
Project-URL: Source Code, https://gitlab.com/codedump2/emmi/
Project-URL: Bug Tracker, https://gitlab.com/codedump2/emmi/-/issues
Classifier: Programming Language :: Python :: 3
Classifier: License :: OSI Approved :: GNU General Public License v3 or later (GPLv3+)
Classifier: Operating System :: POSIX :: Linux
Classifier: Development Status :: 2 - Pre-Alpha
Classifier: Environment :: Console
Classifier: Intended Audience :: Science/Research
Classifier: Topic :: Scientific/Engineering
Requires-Python: >=3.8
License-File: LICENSE
Requires-Dist: schema
Requires-Dist: pyvisa
Requires-Dist: pyvisa-py
Requires-Dist: numpy
Requires-Dist: xarray
Requires-Dist: pyyaml
Requires-Dist: cachetools
Provides-Extra: test
Requires-Dist: pytest; extra == "test"
Requires-Dist: pytest-cov; extra == "test"
Requires-Dist: pyvisa-sim; extra == "test"
Requires-Dist: pytest-asyncio; extra == "test"
Provides-Extra: scpi
Requires-Dist: parse; extra == "scpi"
Requires-Dist: zeroconf; extra == "scpi"
Requires-Dist: psutil; extra == "scpi"
Requires-Dist: asyncio; extra == "scpi"
Provides-Extra: softioc
Requires-Dist: softioc; extra == "softioc"
Provides-Extra: caproto
Requires-Dist: caproto; extra == "caproto"
Provides-Extra: otel
Requires-Dist: opentelemetry-api; extra == "otel"
Requires-Dist: opentelemetry-exporter-otlp; extra == "otel"
Provides-Extra: all
Requires-Dist: emmi[caproto,otel,scpi,test]; extra == "all"
